eventiq_asb/__about__.py
eventiq_asb/__init__.py
eventiq_asb/broker.py
eventiq_asb/middlewares.py
eventiq_asb/py.typed
eventiq_asb/results.py
eventiq_asb/settings.py
eventiq_asb-0.1.9.dist-info/METADATA
eventiq_asb-0.1.9.dist-info/WHEEL
eventiq_asb-0.1.9.dist-info/licenses/LICENSE
eventiq_asb-0.1.9.dist-info/RECORD
