Metadata-Version: 2.3
Name: eventiq-asb
Version: 0.1.9
Summary: Azure Service Bus broker implementation for eventiq
Project-URL: Documentation, https://github.com/asynq-io/eventiq-asb#readme
Project-URL: Issues, https://github.com/asynq-io/eventiq-asb/issues
Project-URL: Source, https://github.com/asynq-io/eventiq-asb
License-Expression: Apache-2.0
License-File: LICENSE
Classifier: Development Status :: 4 - Beta
Classifier: Programming Language :: Python
Classifier: Programming Language :: Python :: 3.9
Classifier: Programming Language :: Python :: 3.10
Classifier: Programming Language :: Python :: 3.11
Classifier: Programming Language :: Python :: 3.12
Classifier: Programming Language :: Python :: Implementation :: CPython
Classifier: Programming Language :: Python :: Implementation :: PyPy
Requires-Python: >=3.9
Requires-Dist: azure-servicebus
Requires-Dist: eventiq>=1.1.2
Provides-Extra: aiohttp
Requires-Dist: aiohttp<4.0,>3.9.0; extra == 'aiohttp'
